torch_grammar/__init__.py
torch_grammar/grammar_parser.py
torch_grammar/grammar_sampler.py
torch_grammar/token_trie.py
torch_grammar-0.3.3.dist-info/METADATA
torch_grammar-0.3.3.dist-info/WHEEL
torch_grammar-0.3.3.dist-info/RECORD
