Metadata-Version: 2.1
Name: torch-grammar
Version: 0.3.3
Summary: Restrict LLM generations to a context-free grammar
License: MIT
Author: Burke Libbey
Author-email: burke.libbey@shopify.com
Requires-Python: >=3.9,<4.0
Classifier: License :: OSI Approved :: MIT License
Classifier: Programming Language :: Python :: 3
Classifier: Programming Language :: Python :: 3.9
Classifier: Programming Language :: Python :: 3.10
Classifier: Programming Language :: Python :: 3.11
Requires-Dist: sentencepiece (>=0.1.99,<0.2.0)
Requires-Dist: torch (>=2.0.0,<3.0.0)
Requires-Dist: transformers (>=4.29,<5.0)
